bhinneka/__init__.py
bhinneka/airport_data.py
bhinneka/cli.py
bhinneka/models.py
bhinneka/server.py
bhinneka/tools/__init__.py
bhinneka/tools/flights.py
bhinneka/tools/searx.py
bhinneka-0.2.0.dist-info/METADATA
bhinneka-0.2.0.dist-info/WHEEL
bhinneka-0.2.0.dist-info/entry_points.txt
bhinneka-0.2.0.dist-info/RECORD
