Metadata-Version: 2.4
Name: bhinneka
Version: 0.2.0
Summary: Unified MCP toolkit: Google Flights utilities and SearXNG web search
Author-email: Batista Harahap <batista@bango29.com>
Requires-Python: >=3.8
Requires-Dist: fast-flights>=2.2
Requires-Dist: fastmcp>=2.12.3
Requires-Dist: httpx>=0.28.1
Requires-Dist: rich>=14.1.0
Requires-Dist: typer>=0.17.4
